[
  {
    "_metadata": {
      "extracted_at": "2026-01-14T05:17:24.780611",
      "file_path": "data/silver/user_collaboration_metrics.json",
      "record_count": 13
    }
  },
  {
    "user": "danrleypereira",
    "collaborator_count": 12,
    "collaborators": [
      "matjack1",
      "Drahkir",
      "epatarroyo",
      "hoffmanc",
      "rulrok",
      "etagwerker",
      "madeindjs",
      "potomak",
      "dependabot[bot]",
      "morrme",
      "pirosm1",
      "jwsloan"
    ],
    "repositories_contributed": 4
  },
  {
    "user": "matjack1",
    "collaborator_count": 12,
    "collaborators": [
      "danrleypereira",
      "Drahkir",
      "epatarroyo",
      "hoffmanc",
      "rulrok",
      "etagwerker",
      "madeindjs",
      "potomak",
      "dependabot[bot]",
      "morrme",
      "pirosm1",
      "jwsloan"
    ],
    "repositories_contributed": 1
  },
  {
    "user": "Drahkir",
    "collaborator_count": 12,
    "collaborators": [
      "danrleypereira",
      "matjack1",
      "epatarroyo",
      "hoffmanc",
      "rulrok",
      "etagwerker",
      "madeindjs",
      "potomak",
      "dependabot[bot]",
      "morrme",
      "pirosm1",
      "jwsloan"
    ],
    "repositories_contributed": 1
  },
  {
    "user": "hoffmanc",
    "collaborator_count": 12,
    "collaborators": [
      "danrleypereira",
      "matjack1",
      "Drahkir",
      "epatarroyo",
      "rulrok",
      "etagwerker",
      "madeindjs",
      "potomak",
      "dependabot[bot]",
      "morrme",
      "pirosm1",
      "jwsloan"
    ],
    "repositories_contributed": 1
  },
  {
    "user": "epatarroyo",
    "collaborator_count": 12,
    "collaborators": [
      "danrleypereira",
      "matjack1",
      "Drahkir",
      "hoffmanc",
      "rulrok",
      "etagwerker",
      "madeindjs",
      "potomak",
      "dependabot[bot]",
      "morrme",
      "pirosm1",
      "jwsloan"
    ],
    "repositories_contributed": 1
  },
  {
    "user": "rulrok",
    "collaborator_count": 12,
    "collaborators": [
      "danrleypereira",
      "matjack1",
      "Drahkir",
      "epatarroyo",
      "hoffmanc",
      "etagwerker",
      "madeindjs",
      "potomak",
      "dependabot[bot]",
      "morrme",
      "pirosm1",
      "jwsloan"
    ],
    "repositories_contributed": 1
  },
  {
    "user": "etagwerker",
    "collaborator_count": 12,
    "collaborators": [
      "danrleypereira",
      "matjack1",
      "Drahkir",
      "epatarroyo",
      "hoffmanc",
      "rulrok",
      "madeindjs",
      "potomak",
      "dependabot[bot]",
      "morrme",
      "pirosm1",
      "jwsloan"
    ],
    "repositories_contributed": 1
  },
  {
    "user": "madeindjs",
    "collaborator_count": 12,
    "collaborators": [
      "danrleypereira",
      "matjack1",
      "Drahkir",
      "epatarroyo",
      "hoffmanc",
      "rulrok",
      "etagwerker",
      "potomak",
      "dependabot[bot]",
      "morrme",
      "pirosm1",
      "jwsloan"
    ],
    "repositories_contributed": 1
  },
  {
    "user": "potomak",
    "collaborator_count": 12,
    "collaborators": [
      "danrleypereira",
      "matjack1",
      "Drahkir",
      "epatarroyo",
      "hoffmanc",
      "rulrok",
      "etagwerker",
      "madeindjs",
      "morrme",
      "dependabot[bot]",
      "pirosm1",
      "jwsloan"
    ],
    "repositories_contributed": 1
  },
  {
    "user": "dependabot[bot]",
    "collaborator_count": 12,
    "collaborators": [
      "danrleypereira",
      "matjack1",
      "Drahkir",
      "epatarroyo",
      "hoffmanc",
      "rulrok",
      "etagwerker",
      "madeindjs",
      "potomak",
      "morrme",
      "pirosm1",
      "jwsloan"
    ],
    "repositories_contributed": 1
  },
  {
    "user": "morrme",
    "collaborator_count": 12,
    "collaborators": [
      "danrleypereira",
      "matjack1",
      "Drahkir",
      "epatarroyo",
      "hoffmanc",
      "rulrok",
      "etagwerker",
      "madeindjs",
      "potomak",
      "dependabot[bot]",
      "pirosm1",
      "jwsloan"
    ],
    "repositories_contributed": 1
  },
  {
    "user": "pirosm1",
    "collaborator_count": 12,
    "collaborators": [
      "danrleypereira",
      "matjack1",
      "Drahkir",
      "epatarroyo",
      "hoffmanc",
      "rulrok",
      "etagwerker",
      "madeindjs",
      "potomak",
      "dependabot[bot]",
      "morrme",
      "jwsloan"
    ],
    "repositories_contributed": 1
  },
  {
    "user": "jwsloan",
    "collaborator_count": 12,
    "collaborators": [
      "danrleypereira",
      "matjack1",
      "Drahkir",
      "epatarroyo",
      "hoffmanc",
      "rulrok",
      "etagwerker",
      "madeindjs",
      "potomak",
      "dependabot[bot]",
      "morrme",
      "pirosm1"
    ],
    "repositories_contributed": 1
  }
]